setup.py
dexcell.egg-info/PKG-INFO
dexcell.egg-info/SOURCES.txt
dexcell.egg-info/dependency_links.txt
dexcell.egg-info/requires.txt
dexcell.egg-info/top_level.txt
dexma/__init__.py
dexma/dexcell.py
test/test_remote_logger.py