Metadata-Version: 1.1
Name: dexcell
Version: 0.4.6
Summary: DEXCell Energy Manager HTTP/JSON REST API for python
Home-page: https://github.com/dexma/dexcell-python/
Author: Jordi Soucheiron
Author-email: jsoucheiron@dexmatetch.com
License: BSD
Platform: UNKNOWN
Classifier: Development Status :: 5 - Production/Stable
Classifier: Environment :: Web Environment
Classifier: Intended Audience :: Developers
Classifier: License :: OSI Approved :: BSD License
Classifier: Operating System :: OS Independent
Classifier: Programming Language :: Python
Classifier: Topic :: Software Development :: Libraries
Classifier: Topic :: Software Development :: Libraries :: Python Modules
Classifier: Topic :: Internet :: WWW/HTTP
Classifier: Programming Language :: Python :: 3
